scriptedsketches/__init__.py
scriptedsketches/cli.py
scriptedsketches/code_generation.py
scriptedsketches/prompt_templates.py
scriptedsketches/scripted_art.py
scriptedsketches-0.1.0.dist-info/LICENSE
scriptedsketches-0.1.0.dist-info/METADATA
scriptedsketches-0.1.0.dist-info/WHEEL
scriptedsketches-0.1.0.dist-info/entry_points.txt
scriptedsketches-0.1.0.dist-info/top_level.txt
scriptedsketches-0.1.0.dist-info/RECORD
