Metadata-Version: 2.1
Name: scriptedsketches
Version: 0.1.0
Summary: A package that allows you to create terminal art powered by GPT-4
Home-page: https://github.com/yourusername/scriptedsketches
Author: Jacob Lapkin
Author-email: jacobglapkin@gmail.com
License: MIT
Keywords: terminal art gpt-4-turbo
Classifier: Programming Language :: Python :: 3
Classifier: License :: OSI Approved :: MIT License
Classifier: Operating System :: OS Independent
Requires-Python: >=3.6
License-File: LICENSE
Requires-Dist: annotated-types >=0.6.0
Requires-Dist: anyio >=4.2.0
Requires-Dist: certifi >=2024.2.2
Requires-Dist: distro >=1.9.0
Requires-Dist: h11 >=0.14.0
Requires-Dist: httpcore >=1.0.2
Requires-Dist: httpx >=0.26.0
Requires-Dist: idna >=3.6
Requires-Dist: openai >=1.10.0
Requires-Dist: pydantic >=2.6.0
Requires-Dist: pydantic-core >=2.16.1
Requires-Dist: python-dotenv >=1.0.1
Requires-Dist: tqdm >=4.66.1
Requires-Dist: typing-extensions >=4.9.0
